HttpTester
